[{"title":"2021/22 동계방학 대기업 직무적성검사 집중교육 2021/22 동계방학 대기업 직무적성검사 집중교육","department":"진로취업센터","date":"2022-02-07T14:00:00+09:00","imageUrl":"https://fun.ssu.ac.kr/attachment/view/88420/cover.jpg?ts\u003d0"},{"title":"2022년 설렘독서캠프 설렘독서캠프 2차 2022년 설렘독서캠프","department":"중앙도서관","date":"2022-02-07T09:00:00+09:00","imageUrl":"https://fun.ssu.ac.kr/attachment/view/87295/cover.jpg?ts\u003d0"},{"title":"2021년 현직자 멘토와 함께하는 직무특강 마케팅(eCommerce) 2021년 현직자 멘토와 함께하는 직무특강","department":"진로취업센터","date":"2022-02-04T19:00:00+09:00","imageUrl":"https://fun.ssu.ac.kr/attachment/view/88342/cover.jpg?ts\u003d0"},{"title":"2021년 현직자 멘토와 함께하는 직무특강 IT개발 2021년 현직자 멘토와 함께하는 직무특강","department":"진로취업센터","date":"2022-02-04T19:00:00+09:00","imageUrl":"https://fun.ssu.ac.kr/attachment/view/88342/cover.jpg?ts\u003d0"},{"title":"2022년 설렘독서캠프 설렘독서캠프 1차 2022년 설렘독서캠프","department":"중앙도서관","date":"2022-01-27T09:00:00+09:00","imageUrl":"https://fun.ssu.ac.kr/attachment/view/87295/cover.jpg?ts\u003d0"},{"title":"(글로벌통상학과)2021학년도 겨울학기 전공한국어 특강 전공한국어 특강_해외직접투자의 기초 이해 (글로벌통상학과)2021학년도 겨울학기 전공한국어 특강","department":"경제통상대학","date":"2022-01-25T09:00:00+09:00","imageUrl":"https://fun.ssu.ac.kr/attachment/view/87629/cover.jpg?ts\u003d0"},{"title":"(글로벌통상학과)2021학년도 겨울학기 전공한국어 특강 전공한국어 특강_국제통상협정론에 대한 접근: 기본 용어를 중심으로 (글로벌통상학과)2021학년도 겨울학기 전공한국어 특강","department":"경제통상대학","date":"2022-01-25T09:00:00+09:00","imageUrl":"https://fun.ssu.ac.kr/attachment/view/87629/cover.jpg?ts\u003d0"},{"title":"(글로벌통상학과)2021학년도 겨울학기 전공한국어 특강 전공한국어 특강_해외시장조사론 (글로벌통상학과)2021학년도 겨울학기 전공한국어 특강","department":"경제통상대학","date":"2022-01-25T09:00:00+09:00","imageUrl":"https://fun.ssu.ac.kr/attachment/view/87629/cover.jpg?ts\u003d0"},{"title":"(글로벌통상학과)2021학년도 겨울학기 전공한국어 특강 전공한국어 특강_국제상무의 이해 (글로벌통상학과)2021학년도 겨울학기 전공한국어 특강","department":"경제통상대학","date":"2022-01-25T09:00:00+09:00","imageUrl":"https://fun.ssu.ac.kr/attachment/view/87629/cover.jpg?ts\u003d0"},{"title":"(글로벌통상학과)2021학년도 겨울학기 전공한국어 특강 전공한국어 특강_국제결제관련 기초 무역용어 (글로벌통상학과)2021학년도 겨울학기 전공한국어 특강","department":"경제통상대학","date":"2022-01-25T09:00:00+09:00","imageUrl":"https://fun.ssu.ac.kr/attachment/view/87629/cover.jpg?ts\u003d0"},{"title":"(글로벌통상학과)2021학년도 겨울학기 전공한국어 특강 전공한국어 특강_사례로 보는 통상한국어 (글로벌통상학과)2021학년도 겨울학기 전공한국어 특강","department":"경제통상대학","date":"2022-01-25T09:00:00+09:00","imageUrl":"https://fun.ssu.ac.kr/attachment/view/87629/cover.jpg?ts\u003d0"},{"title":"(글로벌통상학과)2021학년도 겨울학기 전공한국어 특강 전공한국어 특강_국제운송론 기초 한국어 (글로벌통상학과)2021학년도 겨울학기 전공한국어 특강","department":"경제통상대학","date":"2022-01-25T09:00:00+09:00","imageUrl":"https://fun.ssu.ac.kr/attachment/view/87629/cover.jpg?ts\u003d0"}]